tiepy/__init__.py
tiepy/_version.py
tiepy/tests/__init__.py
tiepy/tests/conftest.py
tiepy/tests/test_examples.py
tiepy_xfel-0.0.2.dist-info/AUTHORS.rst
tiepy_xfel-0.0.2.dist-info/LICENSE
tiepy_xfel-0.0.2.dist-info/METADATA
tiepy_xfel-0.0.2.dist-info/WHEEL
tiepy_xfel-0.0.2.dist-info/top_level.txt
tiepy_xfel-0.0.2.dist-info/RECORD
