Metadata-Version: 2.1
Name: tiepy-xfel
Version: 0.0.2
Summary: Solutions to the Transport of Intensity Equation in Python
Home-page: https://github.com/twguest/tiepy
Author: Trey Guest
Author-email: trey.guest@xfel.eu
License: BSD (3-clause)
Classifier: Development Status :: 2 - Pre-Alpha
Classifier: Natural Language :: English
Classifier: Programming Language :: Python :: 3
Requires-Python: >=3.7
License-File: LICENSE
License-File: AUTHORS.rst
Requires-Dist: numpy
Requires-Dist: scipy
Requires-Dist: matplotlib
Requires-Dist: imageio
